zooper_datasets/premiumhandbags8.py
zooper_datasets-0.1.2.dist-info/LICENSE
zooper_datasets-0.1.2.dist-info/METADATA
zooper_datasets-0.1.2.dist-info/WHEEL
zooper_datasets-0.1.2.dist-info/top_level.txt
zooper_datasets-0.1.2.dist-info/RECORD
