Metadata-Version: 2.1
Name: zooper-datasets
Version: 0.1.2
Summary: This package contains datasets library
Home-page: https://www.zooper.co
Author: Zooper Inc
Author-email: hi@peach.com
License: Apache License, Version 2.0
Keywords: datasets
Platform: UNKNOWN
Classifier: Development Status :: 3 - Alpha
Classifier: Intended Audience :: Developers
Classifier: Natural Language :: English
Classifier: Operating System :: POSIX :: Linux
Classifier: Programming Language :: Python :: 3.6
Classifier: License :: OSI Approved :: Apache Software License
